groupster/__init__.py
groupster/cohort.py
groupster/group.py
groupster/play.ipynb
groupster/solver.py
groupster/util.py
groupster-2025.4.0.dist-info/METADATA
groupster-2025.4.0.dist-info/WHEEL
groupster-2025.4.0.dist-info/licenses/LICENSE
groupster-2025.4.0.dist-info/RECORD
