Metadata-Version: 2.4
Name: groupster
Version: 2025.4.0
Summary: Python package for building diverse and fair groups.
Project-URL: Repository, https://github.com/teachnology/groupster
Author-email: Marijan Beg <m.beg@imperial.ac.uk>
License-Expression: MIT
License-File: LICENSE
Keywords: diversity,edi,fairness,groups,higher education,inclusion,teambuilding,teams
Classifier: Development Status :: 5 - Production/Stable
Classifier: Intended Audience :: Education
Classifier: License :: OSI Approved :: MIT License
Classifier: Natural Language :: English
Classifier: Operating System :: OS Independent
Requires-Python: >=3.13
Requires-Dist: fakeitmakeit>=2024.11.0
Requires-Dist: pandas>=2.2.3
Requires-Dist: tqdm>=4.67.1
